[
    {
     "id": 1,
     "full_name": "Wendall Gripton",
     "email": "wg@creative.org",
     "gender": "Male",
     "age": 100,
     "start_date": "2022-01-26"
    },
    {
        "id": 2,
        "full_name": "Campbell Compton",
        "email": "2f@creative.org",
        "gender": "Female",
        "age": 50,
        "start_date": "2022-01-26"
       },
       {
        "id": 3,
        "full_name": "Naomi Compton",
        "email": "wf@creative.org",
        "gender": "Female",
        "age": 40,
        "start_date": "2022-01-22"
       },
       {
        "id": 4,
        "full_name": "Riley Jackson",
        "email": "lh@creative.org",
        "gender": "Male",
        "age": 50,
        "start_date": "2020-01-26"
       },
       {
        "id": 5,
        "full_name": "Freeman Umaru",
        "email": "jj@creative.org",
        "gender": "Male",
        "age": 30,
        "start_date": "2022-05-16"
       },
       {
           "id": 6,
           "full_name": "Highlife Hamai",
           "email": "2f@creative.org",
           "gender": "Female",
           "age": 25,
           "start_date": "2021-03-22"
          },
          {
           "id": 7,
           "full_name": "Peace Blessing",
           "email": "pb@creative.org",
           "gender": "Male",
           "age": 32,
           "start_date": "2021-03-22"
          },
          {
            "id": 8,
            "full_name": null,
            "email": "nn@creative.org",
            "gender": "Male",
            "age": null,
            "start_date": "2021-03-22"
           },
           {
            "id": 9,
            "full_name": "Ope Annie",
            "email": null,
            "gender": "Male",
            "age": 32,
            "start_date": null
           },
          {
           "id": 10,
           "full_name": "McCarter Neon",
           "email": "mn@creative.org",
           "gender": "Female",
           "age": 20,
           "start_date": "2023-09-26"
          }
   ]